cjggg060615/__init__.py
cjggg060615/cjggg060615.py
cjggg060615-0.1.dist-info/METADATA
cjggg060615-0.1.dist-info/WHEEL
cjggg060615-0.1.dist-info/top_level.txt
cjggg060615-0.1.dist-info/RECORD
