Metadata-Version: 2.1
Name: cjggg060615
Version: 0.1
Summary: Python functions for controlling Arduino devices
Author: wowogud
Author-email: jhc06150615@gmail.com
Requires-Dist: pyserial
